caqtus_devices/arbitrary_waveform_generators/siglent_sdg6000x/__init__.py
caqtus_devices/arbitrary_waveform_generators/siglent_sdg6000x/_compiler.py
caqtus_devices/arbitrary_waveform_generators/siglent_sdg6000x/_configuration.py
caqtus_devices/arbitrary_waveform_generators/siglent_sdg6000x/_controller.py
caqtus_devices/arbitrary_waveform_generators/siglent_sdg6000x/_editor.py
caqtus_devices/arbitrary_waveform_generators/siglent_sdg6000x/_extension.py
caqtus_devices/arbitrary_waveform_generators/siglent_sdg6000x/_proxy.py
caqtus_devices/arbitrary_waveform_generators/siglent_sdg6000x/_runtime.py
caqtus_devices/arbitrary_waveform_generators/siglent_sdg6000x/py.typed
caqtus_devices/arbitrary_waveform_generators/siglent_sdg6000x/sine_editor.ui
caqtus_devices/arbitrary_waveform_generators/siglent_sdg6000x/sine_editor_ui.py
caqtus_devices_siglent_sdg6000x-2.7.2.dist-info/METADATA
caqtus_devices_siglent_sdg6000x-2.7.2.dist-info/WHEEL
caqtus_devices_siglent_sdg6000x-2.7.2.dist-info/licenses/license.md
caqtus_devices_siglent_sdg6000x-2.7.2.dist-info/RECORD
