Metadata-Version: 2.4
Name: caqtus-devices-siglent-sdg6000x
Version: 2.7.2
Summary: Contains extension code for caqtus framework for siglent arbitrary waveform generators SDG6000X
Author-email: light-scattering-io <lecaqtus66@gmail.com>
License: Copyright 2024 Université Paris-Saclay
License-File: license.md
Requires-Python: >=3.12
Requires-Dist: caqtus-suite>=6.18.1
Requires-Dist: pyside6!=6.8.1.1,>=6.8.1
Requires-Dist: pyvisa>=1.14.1
